README.rst
setup.cfg
setup.py
sympa/__init__.py
sympa/core.py
sympa.egg-info/PKG-INFO
sympa.egg-info/SOURCES.txt
sympa.egg-info/dependency_links.txt
sympa.egg-info/top_level.txt