Metadata-Version: 1.1
Name: sympa
Version: 0.1.0
Summary: Symbolic math for pandas
Home-page: https://github.com/jnmclarty/sympa
Author: Jeffrey McLarty
Author-email: jeffrey.mclarty@gmail.com
License: UNKNOWN
Download-URL: https://github.com/jnmclarty/sympa/tarball/0.1.0
Keywords: symbolic,symbol,sympa,sympy,pandas,math
Platform: UNKNOWN
Classifier: Development Status :: 1 - Planning
Classifier: License :: OSI Approved :: MIT License
Classifier: Intended Audience :: Developers
Classifier: Intended Audience :: Education
Classifier: Intended Audience :: Financial and Insurance Industry
Classifier: Intended Audience :: Healthcare Industry
Classifier: Intended Audience :: Science/Research
Classifier: Operating System :: OS Independent
Classifier: Programming Language :: Python :: 2.7
Classifier: Topic :: Scientific/Engineering
Classifier: Topic :: Scientific/Engineering :: Mathematics
